billi_image-1.0.2.dist-info/licenses/LICENSE
image_format_library/__init__.py
image_format_library/cli.py
image_format_library/core.py
billi_image-1.0.2.dist-info/METADATA
billi_image-1.0.2.dist-info/WHEEL
billi_image-1.0.2.dist-info/entry_points.txt
billi_image-1.0.2.dist-info/top_level.txt
billi_image-1.0.2.dist-info/RECORD
