Metadata-Version: 2.4
Name: billi-image
Version: 1.0.2
Summary: A flexible library for custom image format encoding and decoding
Author-email: Ansh Sharma <anshsxa@gmail.com>
License: MIT
Project-URL: Homepage, https://github.com/anshxs/billi-image
Project-URL: Bug Reports, https://github.com/anshxs/billi-image/issues
Project-URL: Source, https://github.com/anshxs/billi-image
Project-URL: Documentation, https://github.com/anshxs/billi-image/blob/main/README.md
Keywords: image,compression,format,encoding,decoding,billi
Classifier: Development Status :: 4 - Beta
Classifier: Intended Audience :: Developers
Classifier: License :: OSI Approved :: MIT License
Classifier: Operating System :: OS Independent
Classifier: Programming Language :: Python :: 3
Classifier: Programming Language :: Python :: 3.7
Classifier: Programming Language :: Python :: 3.8
Classifier: Programming Language :: Python :: 3.9
Classifier: Programming Language :: Python :: 3.10
Classifier: Programming Language :: Python :: 3.11
Classifier: Programming Language :: Python :: 3.12
Classifier: Topic :: Multimedia :: Graphics
Classifier: Topic :: Software Development :: Libraries :: Python Modules
Requires-Python: >=3.7
License-File: LICENSE
Requires-Dist: Pillow>=8.0.0
Provides-Extra: dev
Requires-Dist: pytest>=6.0; extra == "dev"
Requires-Dist: pytest-cov; extra == "dev"
Requires-Dist: black; extra == "dev"
Requires-Dist: flake8; extra == "dev"
Requires-Dist: mypy; extra == "dev"
Dynamic: license-file
